pyGuifiAPI/__init__.py
pyGuifiAPI/error.py
pyGuifiAPI/api.py
pyGuifiAPI/constants.py
pyGuifiAPI/tests/getManufacturers.py
pyGuifiAPI/tests/updateNode.py
pyGuifiAPI/tests/removeNode.py
pyGuifiAPI/tests/addInterface.py
pyGuifiAPI/tests/addDevice.py
pyGuifiAPI/tests/removeLink.py
pyGuifiAPI/tests/guifiConfig.py
pyGuifiAPI/tests/getChannels.py
pyGuifiAPI/tests/removeInterface.py
pyGuifiAPI/tests/addRadio.py
pyGuifiAPI/tests/addLink.py
pyGuifiAPI/tests/removeRadio.py
pyGuifiAPI/tests/getModels.py
pyGuifiAPI/tests/removeDevice.py
pyGuifiAPI/tests/getProtocols.py
pyGuifiAPI/tests/getFirmwares.py
pyGuifiAPI/tests/addNode.py
pyGuifiAPI/tests/guifiConfig.py.example
pyGuifiAPI/tests/guifiConfig.pyc
pyGuifiAPI/examples/getManufacturers.py
pyGuifiAPI/examples/updateNode.py
pyGuifiAPI/examples/updateLink.py
pyGuifiAPI/examples/updateZone.py
pyGuifiAPI/examples/removeNode.py
pyGuifiAPI/examples/addInterface.py
pyGuifiAPI/examples/updateDevice.py
pyGuifiAPI/examples/updateRadio.py
pyGuifiAPI/examples/addDevice.py
pyGuifiAPI/examples/removeLink.py
pyGuifiAPI/examples/guifiConfig.py
pyGuifiAPI/examples/getChannels.py
pyGuifiAPI/examples/removeInterface.py
pyGuifiAPI/examples/addRadio.py
pyGuifiAPI/examples/addLink.py
pyGuifiAPI/examples/removeRadio.py
pyGuifiAPI/examples/getModels.py
pyGuifiAPI/examples/removeDevice.py
pyGuifiAPI/examples/getProtocols.py
pyGuifiAPI/examples/getFirmwares.py
pyGuifiAPI/examples/addNode.py
pyGuifiAPI/examples/guifiConfig.py.example
pyGuifiAPI/examples/guifiConfig.pyc
pyGuifiAPI-0.8.dist-info/WHEEL
pyGuifiAPI-0.8.dist-info/RECORD
pyGuifiAPI-0.8.dist-info/top_level.txt
pyGuifiAPI-0.8.dist-info/metadata.json
pyGuifiAPI-0.8.dist-info/DESCRIPTION.rst
pyGuifiAPI-0.8.dist-info/METADATA
pyGuifiAPI-0.8.data/data/CHANGES.md
pyGuifiAPI-0.8.data/data/LICENSE.txt
pyGuifiAPI-0.8.data/data/README.md
