Metadata-Version: 2.0
Name: pyGuifiAPI
Version: 0.8
Summary: A Python interface for the Guifi.net API
Home-page: https://github.com/PabloCastellano/pyGuifiAPI/
Author: Pablo Castellano
Author-email: pablo@anche.no
License: GPLv3+
Download-URL: https://github.com/PabloCastellano/pyGuifiAPI/archive/master.zip
Keywords: free networks,guifi.net,API
Platform: UNKNOWN
Classifier: Programming Language :: Python :: 2
Classifier: Programming Language :: Python :: 3
